darwin.cpython-38-x86_64-linux-gnu.so
darwin_framework-1.0.dist-info/WHEEL
darwin_framework-1.0.dist-info/RECORD
darwin_framework-1.0.dist-info/METADATA
darwin_framework-1.0.dist-info/top_level.txt
