Metadata-Version: 2.1
Name: darwin-framework
Version: 1.0
Summary: Darwin Framework
Home-page: https://github.com/tlemo/darwin
Author: Leonard Mosescu
Author-email: lemo1234@gmail.com
License: Apache License 2.0
Platform: UNKNOWN
Classifier: Programming Language :: Python
Classifier: Programming Language :: Python :: 3
Classifier: Programming Language :: C++
Classifier: License :: OSI Approved :: Apache Software License
Classifier: Operating System :: Microsoft :: Windows
Classifier: Operating System :: POSIX :: Linux
Classifier: Topic :: Scientific/Engineering :: Artificial Intelligence
Requires-Python: >=3.6
